entities/__init__.py
entities/abstract_settings.py
entities/directory_settings.py
entities/settings.py
settings/__init__.py
settings/main.py
tests/__init__.py
tests/test_directory_settings.py
tests/test_settings.py
tests/example/__init__.py
tests/example/api.py
tests/example/db.py
settings_master-0.1.0.dist-info/METADATA
settings_master-0.1.0.dist-info/WHEEL
settings_master-0.1.0.dist-info/top_level.txt
settings_master-0.1.0.dist-info/RECORD
