Metadata-Version: 2.1
Name: settings-master
Version: 0.1.0
Summary: UNKNOWN
Home-page: https://github.com/semenInRussia/FreeSpotify_back
Author: semenInRussia
Author-email: hrams205@gmail.com
License: MIT
Platform: UNKNOWN
Requires-Dist: python-dotenv (~=0.15.0)
